cpr_gym_engine.so
cpr_gym/envs.py
cpr_gym/__init__.py
cpr_gym/wrappers.py
cpr_gym/__main__.py
cpr_gym-0.7.0.dist-info/RECORD
cpr_gym-0.7.0.dist-info/WHEEL
cpr_gym-0.7.0.dist-info/top_level.txt
cpr_gym-0.7.0.dist-info/METADATA
