Metadata-Version: 2.1
Name: cpr-gym
Version: 0.7.0
Summary: Gym environment for attacking proof-of-work protocols with RL
Home-page: https://github.com/pkel/cpr
Author: Patrik Keller
Author-email: git@pkel.dev
Keywords: proof-of-work consensus rl gym selfish-mining reinforcement-learning
Classifier: Development Status :: 4 - Beta
Classifier: Intended Audience :: Science/Research
Classifier: Programming Language :: OCaml
Classifier: Programming Language :: Python :: 3
Classifier: Topic :: Security
Requires-Dist: gym
Requires-Dist: numpy
